mux4to1.v
module mux4to1(input[3:0]i,
               input[1:0]s,
               output y);
always @ (*)begin
if (s == 2'b00) y=i[0];
else if (s==2'b01) y=i[1];
else if (s==2'b10) y=i[2];
else if (s==2'b11) y=i[3];
end
endmodule

mux4to1_tb.v
module tb_mux4to1;
reg [3:0]i;
reg [1:0]s;
wire y;
mux4to1 uut(.i(i),
            .s(s),
	    .y(y));
initial begin;
$dumpfile("mux4to1.vcd");
$dumpvars(0,tb_mux4to1); 
$monitor("i=%b s=%b y=%b", i,s,y);
i=4'b1010;
s=2'b00;#10
s=2'b01;#10
s=2'b10;#10
s=2'b11;#10
i=4'b1100;
s=2'b00;#10
s=2'b01;#10
s=2'b10;#10
s=2'b11;#10
$finish;
end
endmodule

mux4to1.vcd
$date
	Wed Apr  8 11:51:11 2026
$end
$version
	Icarus Verilog
$end
$timescale
	1s
$end
$scope module tb_mux4to1 $end
$var wire 1 ! y $end
$var reg 4 " i [3:0] $end
$var reg 2 # s [1:0] $end
$scope module uut $end
$var wire 4 $ i [3:0] $end
$var wire 2 % s [1:0] $end
$var reg 1 ! y $end
$upscope $end
$upscope $end
$enddefinitions $end
$comment Show the parameter values. $end
$dumpall
$end
#0
$dumpvars
b0 %
b1010 $
b0 #
b1010 "
0!
$end
#10
1!
b1 #
b1 %
#20
0!
b10 #
b10 %
#30
1!
b11 #
b11 %
#40
0!
b0 #
b0 %
b1100 "
b1100 $
#50
b1 #
b1 %
#60
1!
b10 #
b10 %
#70
b11 #
b11 %
